MANIFEST.in
README.md
setup.py
lixi/_LIXI.py
lixi/_Message.py
lixi/__init__.py
lixi/_customise_schema.py
lixi/_jsonschema_functions.py
lixi/_path_functions.py
lixi/_schematron_functions.py
lixi/_xml_to_json.py
lixi/_xslt_transform.py
lixi/customization.xsd
lixi/xslts/LIXI-ACC-0_0_2-LIXI-ACC-0_0_3-warnings.zip
lixi/xslts/LIXI-ACC-0_0_2-LIXI-ACC-0_0_3.zip
lixi/xslts/LIXI-ACC-0_0_3-LIXI-ACC-0_0_2-warnings.zip
lixi/xslts/LIXI-ACC-0_0_3-LIXI-ACC-0_0_2.zip
lixi/xslts/LIXI-ACC-0_0_3-LIXI-ACC-0_0_4-warnings.zip
lixi/xslts/LIXI-ACC-0_0_3-LIXI-ACC-0_0_4.zip
lixi/xslts/LIXI-ACC-0_0_4-LIXI-ACC-0_0_3-warnings.zip
lixi/xslts/LIXI-ACC-0_0_4-LIXI-ACC-0_0_3.zip
lixi/xslts/LIXI-ACC-0_0_4-LIXI-ACC-0_0_5-warnings.zip
lixi/xslts/LIXI-ACC-0_0_4-LIXI-ACC-0_0_5.zip
lixi/xslts/LIXI-ACC-0_0_5-LIXI-ACC-0_0_4-warnings.zip
lixi/xslts/LIXI-ACC-0_0_5-LIXI-ACC-0_0_4.zip
lixi/xslts/LIXI-ACC-0_0_5-LIXI-ACC-0_0_6-warnings.zip
lixi/xslts/LIXI-ACC-0_0_5-LIXI-ACC-0_0_6.zip
lixi/xslts/LIXI-ACC-0_0_6-LIXI-ACC-0_0_5-warnings.zip
lixi/xslts/LIXI-ACC-0_0_6-LIXI-ACC-0_0_5.zip
lixi/xslts/LIXI-CAL-2_4_2-LIXI-CAL-2_5_0-warnings.zip
lixi/xslts/LIXI-CAL-2_4_2-LIXI-CAL-2_5_0.zip
lixi/xslts/LIXI-CAL-2_5_0-LIXI-CAL-2_4_2-warnings.zip
lixi/xslts/LIXI-CAL-2_5_0-LIXI-CAL-2_4_2.zip
lixi/xslts/LIXI-CAL-2_5_0-LIXI-CAL-2_6_0-warnings.zip
lixi/xslts/LIXI-CAL-2_5_0-LIXI-CAL-2_6_0.zip
lixi/xslts/LIXI-CAL-2_6_0-LIXI-CAL-2_5_0-warnings.zip
lixi/xslts/LIXI-CAL-2_6_0-LIXI-CAL-2_5_0.zip
lixi/xslts/LIXI-CAL-2_6_0-LIXI-CAL-2_6_1-warnings.zip
lixi/xslts/LIXI-CAL-2_6_0-LIXI-CAL-2_6_1.zip
lixi/xslts/LIXI-CAL-2_6_1-LIXI-CAL-2_6_0-warnings.zip
lixi/xslts/LIXI-CAL-2_6_1-LIXI-CAL-2_6_0.zip
lixi/xslts/LIXI-CAL-2_6_1-LIXI-CAL-2_6_2-warnings.zip
lixi/xslts/LIXI-CAL-2_6_1-LIXI-CAL-2_6_2.zip
lixi/xslts/LIXI-CAL-2_6_10-LIXI-CAL-2_6_11-warnings.zip
lixi/xslts/LIXI-CAL-2_6_10-LIXI-CAL-2_6_11.zip
lixi/xslts/LIXI-CAL-2_6_10-LIXI-CAL-2_6_9-warnings.zip
lixi/xslts/LIXI-CAL-2_6_10-LIXI-CAL-2_6_9.zip
lixi_ammar.egg-info/PKG-INFO
lixi_ammar.egg-info/SOURCES.txt
lixi_ammar.egg-info/dependency_links.txt
lixi_ammar.egg-info/requires.txt
lixi_ammar.egg-info/top_level.txt