Metadata-Version: 2.1
Name: lixi-ammar
Version: 0.0.27
Summary: lixi is a python package to manipulate a valid LIXI message and schema.
Home-page: https://standards.lixi.org.au/lixi-tech/lixi-pypi
Author: Ammar Khan
Author-email: lixilab@lixi.org.au
License: MIT
Platform: UNKNOWN
Classifier: License :: OSI Approved :: MIT License
Classifier: Programming Language :: Python
Classifier: Programming Language :: Python :: 3
